chromospyce/__init__.py
chromospyce/static/widget.css
chromospyce/static/widget.js
chromospyce-0.1.2.dist-info/METADATA
chromospyce-0.1.2.dist-info/WHEEL
chromospyce-0.1.2.dist-info/RECORD
