Metadata-Version: 2.3
Name: chromospyce
Version: 0.1.2
Requires-Python: >=3.8
Requires-Dist: anywidget>=0.9.13
Requires-Dist: numpy>=1.24.4
Requires-Dist: pandas>=2.0.3
Requires-Dist: pyarrow>=17.0.0
